phylotree/__init__.py
phylotree/phylotree.py
plotly_phylotree-0.0.1.dist-info/LICENSE
plotly_phylotree-0.0.1.dist-info/METADATA
plotly_phylotree-0.0.1.dist-info/WHEEL
plotly_phylotree-0.0.1.dist-info/top_level.txt
plotly_phylotree-0.0.1.dist-info/RECORD
