Metadata-Version: 2.1
Name: plotly_phylotree
Version: 0.0.1
Summary: A package to plot phylogenetic trees with Plotly.
Author: voelkerh
License: MIT License
Project-URL: Repository, https://github.com/voelkerh/plotly_phylotree
Classifier: License :: OSI Approved :: MIT License
Classifier: Programming Language :: Python :: 3
Classifier: Operating System :: OS Independent
Requires-Python: >=3.9
License-File: LICENSE
Requires-Dist: plotly
Requires-Dist: biopython
Requires-Dist: numpy
Provides-Extra: dev
Requires-Dist: pytest>=7.0; extra == "dev"
Requires-Dist: twine>=4.0.2; extra == "dev"
